lank/__init__.py
lank/__main__.py
lank/__version__.py
lank/cmd.py
lank/config.py
lank/name.py
lank/registration.py
lank/crypto/__init__.py
lank/crypto/v1.py
lank/node/__init__.py
lank/node/__main__.py
lank/node/cmd.py
lank/node/db.py
lank/node/test.py
lank/node/patch/__init__.py
lank/node/patch/v2.py
lank/node/patch/v3.py
lank/node/patch/v4.py
lank/node/protocol/__init__.py
lank/node/protocol/v1/__init__.py
lank/node/protocol/v1/message.py
lank/node/protocol/v2/__init__.py
lank/node/protocol/v2/ack.py
lank/node/protocol/v2/base.py
lank/node/protocol/v2/deny.py
lank/node/protocol/v2/peer.py
lank/node/protocol/v2/register.py
lank/node/protocol/v2/sync.py
lank/peer/__init__.py
lank/peer/__main__.py
lank/peer/cmd.py
lank/peer/test.py
lank/peer/protocol/__init__.py
lank/peer/protocol/v1/__init__.py
lank/peer/protocol/v1/message.py
lank/peer/protocol/v2/__init__.py
lank/peer/protocol/v2/ack.py
lank/peer/protocol/v2/base.py
lank/peer/protocol/v2/media.py
lank-0.4.7.dist-info/LICENSE
lank-0.4.7.dist-info/METADATA
lank-0.4.7.dist-info/WHEEL
lank-0.4.7.dist-info/entry_points.txt
lank-0.4.7.dist-info/top_level.txt
lank-0.4.7.dist-info/RECORD
