Metadata-Version: 2.1
Name: lank
Version: 0.4.7
Summary: Listening Anchor Nodes for K
Home-page: https://github.com/lannocc/lank
Author: LANNOCC (Shawn A. Wilson)
Author-email: lannocc@yahoo.com
Classifier: Programming Language :: Python :: 3
Classifier: License :: OSI Approved :: MIT License
Classifier: Operating System :: OS Independent
License-File: LICENSE
Requires-Dist: appdirs
Requires-Dist: bidict
Requires-Dist: cryptography (>=37.0.4)
Requires-Dist: gevent
Requires-Dist: ntplib
Requires-Dist: password-strength
